digitalarchive/__init__.py
digitalarchive/api.py
digitalarchive/exceptions.py
digitalarchive/matching.py
digitalarchive/models.py
digitalarchive-0.1.12.dist-info/LICENSE
digitalarchive-0.1.12.dist-info/METADATA
digitalarchive-0.1.12.dist-info/WHEEL
digitalarchive-0.1.12.dist-info/top_level.txt
digitalarchive-0.1.12.dist-info/RECORD
