Metadata-Version: 2.1
Name: digitalarchive
Version: 0.1.12
Summary: A python client for the Wilson Center Digital Archive API.
Home-page: https://github.com/epikulski/digitalarchive
Author: Evan Pikulski
Author-email: epikulsk@gmail.com
License: MIT
Classifier: License :: OSI Approved :: MIT License
Classifier: Programming Language :: Python
Classifier: Programming Language :: Python :: 3
Classifier: Programming Language :: Python :: 3.7
Classifier: Programming Language :: Python :: 3.8
Classifier: Programming Language :: Python :: 3.9
Classifier: Programming Language :: Python :: 3.10
Classifier: Programming Language :: Python :: 3.11
Classifier: Programming Language :: Python :: Implementation :: CPython
Classifier: Programming Language :: Python :: Implementation :: PyPy
Requires-Python: >=3.7.0
License-File: LICENSE
Requires-Dist: httpx
Requires-Dist: pydantic
